turbo_gepa/__init__.py
turbo_gepa/archive.py
turbo_gepa/cache.py
turbo_gepa/config.py
turbo_gepa/evaluator.py
turbo_gepa/interfaces.py
turbo_gepa/islands.py
turbo_gepa/metrics.py
turbo_gepa/migrations.py
turbo_gepa/mutator.py
turbo_gepa/orchestrator.py
turbo_gepa/sampler.py
turbo_gepa/scheduler.py
turbo_gepa/scoring.py
turbo_gepa/seed_initializer.py
turbo_gepa/stop_governor.py
turbo_gepa/telemetry.py
turbo_gepa/adapters/__init__.py
turbo_gepa/adapters/default_adapter.py
turbo_gepa/adapters/dspy_adapter.py
turbo_gepa/distributed/__init__.py
turbo_gepa/distributed/local_multiworker.py
turbo_gepa/distributed/runner.py
turbo_gepa/dspy_utils/__init__.py
turbo_gepa/dspy_utils/instruction_proposal.py
turbo_gepa/evaluators/__init__.py
turbo_gepa/evaluators/llm_judge.py
turbo_gepa/logging/__init__.py
turbo_gepa/logging/logger.py
turbo_gepa/logging/progress.py
turbo_gepa/logging/report.py
turbo_gepa/strategies/__init__.py
turbo_gepa/utils/__init__.py
turbo_gepa/utils/litellm_client.py
turbo_gepa/utils/llm_request_manager.py
turbo_gepa-0.1.6.dist-info/licenses/LICENSE
turbo_gepa-0.1.6.dist-info/METADATA
turbo_gepa-0.1.6.dist-info/WHEEL
turbo_gepa-0.1.6.dist-info/entry_points.txt
turbo_gepa-0.1.6.dist-info/top_level.txt
turbo_gepa-0.1.6.dist-info/RECORD
