Metadata-Version: 2.4
Name: turbo-gepa
Version: 0.1.6
Summary: High-throughput prompt evolution framework - production fork of GEPA with island-based parallelism, async orchestration, and ASHA successive halving.
Author-email: Greg Miller <greg@intrinsic-labs.ai>
License: MIT
Project-URL: Homepage, https://github.com/Studio-Intrinsic/turbo-gepa
Project-URL: Bug Tracker, https://github.com/Studio-Intrinsic/turbo-gepa/issues
Project-URL: Documentation, https://github.com/Studio-Intrinsic/turbo-gepa#readme
Project-URL: Original GEPA, https://github.com/gepa-ai/gepa
Requires-Python: <3.14,>=3.10
License-File: LICENSE
Requires-Dist: litellm>=1.64.0
Requires-Dist: httpx>=0.24
Requires-Dist: xxhash>=3.0.0
Provides-Extra: full
Requires-Dist: litellm>=1.64.0; extra == "full"
Requires-Dist: datasets>=2.14.6; extra == "full"
Requires-Dist: mlflow>=3.0.0; extra == "full"
Requires-Dist: wandb; extra == "full"
Requires-Dist: tqdm>=4.66.1; extra == "full"
Requires-Dist: plotext>=5.2.8; extra == "full"
Requires-Dist: dspy-ai; extra == "full"
Provides-Extra: dspy
Requires-Dist: dspy-ai; extra == "dspy"
Provides-Extra: test
Requires-Dist: turbo-gepa[full]; extra == "test"
Requires-Dist: pytest; extra == "test"
Requires-Dist: pytest-asyncio>=0.21; extra == "test"
Provides-Extra: build
Requires-Dist: setuptools>=77.0.1; extra == "build"
Requires-Dist: wheel; extra == "build"
Requires-Dist: build; extra == "build"
Requires-Dist: twine; extra == "build"
Requires-Dist: semver; extra == "build"
Requires-Dist: packaging; extra == "build"
Requires-Dist: requests; extra == "build"
Provides-Extra: dev
Requires-Dist: turbo-gepa[test]; extra == "dev"
Requires-Dist: turbo-gepa[build]; extra == "dev"
Requires-Dist: pre-commit; extra == "dev"
Requires-Dist: build>=1.0.3; extra == "dev"
Requires-Dist: ruff>=0.3.0; extra == "dev"
Dynamic: license-file
